openreviewio/Content.py
openreviewio/MediaReview.py
openreviewio/Note.py
openreviewio/Status.py
openreviewio/__init__.py
openreviewio/base.py
openreviewio/orio_classes/Content.toml
openreviewio/orio_classes/Image.toml
openreviewio/orio_classes/ImageAnnotation.toml
openreviewio/orio_classes/Note.toml
openreviewio/orio_classes/Review.toml
openreviewio/orio_classes/Status.toml
openreviewio/orio_classes/TextComment.toml
openreviewio-0.0.39.dist-info/LICENCE
openreviewio-0.0.39.dist-info/METADATA
openreviewio-0.0.39.dist-info/WHEEL
openreviewio-0.0.39.dist-info/top_level.txt
openreviewio-0.0.39.dist-info/RECORD
