Metadata-Version: 2.1
Name: openreviewio
Version: 0.0.39
Summary: OpenReviewIO Python API
Home-page: https://gitlab.com/openreviewio/openreviewio_py
Author: Félix David
Author-email: felixg.david@gmail.com
License: License :: OSI Approved :: GNU General Public License v3 or later (GPLv3+)
Platform: UNKNOWN
Classifier: Programming Language :: Python :: 3
Classifier: Operating System :: OS Independent
Requires-Python: >=3.6
Requires-Dist: toml
Requires-Dist: lxml
